{
  "users": {
    "1707382528": {},
    "7617987031": {
      "status_deposit": true,
      "registered": true,
      "username": "rissgtg",
      "name": "Riss",
      "date_registered": "2025-07-03T16:53:25.539Z",
      "saldo": null,
      "panels": [
        {
          "id": 12,
          "username": "jujur",
          "ram": 1000,
          "disk": 1000,
          "cpu": 40,
          "tokenGaransi": "RISSG-DBC6F10D9890",
          "expireGaransi": 1753332642689,
          "createdAt": 1751604642689
        }
      ],
      "saweria": {
        "chat": "7617987031",
        "msg_id": 584,
        "transactionId": "1BA4B03251",
        "amount": "1121",
        "nominal": "1000",
        "createdAt": 1751607161277
      }
    },
    "6212082135": {}
  },
  "chats": {
    "1707382528": {},
    "7617987031": {},
    "6212082135": {}
  },
  "settings": {
    "7593568365": {}
  }
}